[
  {
    "source": "npmjzjfp",
    "source_title": "麻将战绩",
    "msg_id": 2301,
    "shop": "童话镇",
    "girl": "小彤彤",
    "girl_link": "https://t.me/tonghuazhen_xiaofeifei/23682",
    "review_link": "https://t.me/npmjzjfp/2301",
    "shop_tg": "https://t.me/tonghuazhen_fei",
    "time": "10:41",
    "fp": "0f298354be95c52ad7766bb689f702b3",
    "ai_summary": "童话镇小彤彤：萝莉王反差甜妹，态度热情、敏感度高，服务自然投入，综合体验出色。",
    "text_preview": "#牌局复盘\n\n【麻友】：夜雨声烦\n【棋牌室】：#童话镇\n【麻将搭子】：#小彤彤\n【搭子链接】：https://t.me/tonghuazhen_xiaofeifei/23682\n【台费】：新人测评\n【胡牌牌型】： #大班\n【牌局特点】：#萝莉王 #反差奶黄包 #小狗\n【各项得分】：（0-10，6 为及格）\n  环境：7\n  人照：8\n  身材：9\n  皮肤：8\n  态度：9\n  敏感度：10\n  抽烟：无\n  纹身：无\n  各种钉：无\n【综合得分】：9（0-10，6 为及格）\n【牌局体验】：\n\n在童话镇家刷到妹妹的ootd的就心动了，那张嫩嫩的娃娃脸配萝莉王的娇小身材，加上最后几秒的小巧思，肯"
  },
  {
    "source": "npmjzjfp",
    "source_title": "麻将战绩",
    "msg_id": 2300,
    "shop": "Kitty岛",
    "girl": "七七",
    "girl_link": "https://t.me/hello_kittynvpuguan/33653",
    "review_link": "https://t.me/npmjzjfp/2300",
    "shop_tg": "https://t.me/hello_kittynvpuguan",
    "time": "10:39",
    "fp": "cb03fa9d39982504273797f503dffdc1",
    "ai_summary": "Kitty岛七七妹妹，服务配合度高、态度佳，素人感强、沟通自然，综合体验优秀。",
    "text_preview": "#牌局复盘\n\n【麻友】：听泉子\n【棋牌室】：#Kitty岛\n【麻将搭子】：#七七\n【搭子链接】：https://t.me/hello_kittynvpuguan/33653\n【台费】：工兵价\n【胡牌牌型】：#大班\n【牌局特点】：#配合度高\n【各项得分】：（0-10，6 为及格，对应大班）\n  环境：8\n  人照：8.5\n  身材：8.5\n  皮肤：8\n  态度：9\n  敏感度：9\n  抽烟：无\n  纹身：无\n  各种钉：无\n【综合得分】：9\n【牌局体验】：\n\nkitty又上新了，看模卡和ot，颜值身材不错，到了之后碰到了屁屁，说是她闺蜜让我千万要温柔一点，顶着这种压力我只好使出了70%的功力，"
  },
  {
    "source": "npmjzjfp",
    "source_title": "麻将战绩",
    "msg_id": 2299,
    "shop": "Kitty岛",
    "girl": "小乔",
    "girl_link": "https://t.me/hello_kittynvpuguan/33628",
    "review_link": "https://t.me/npmjzjfp/2299",
    "shop_tg": "https://t.me/hello_kittynvpuguan",
    "time": "09:57",
    "fp": "74485f3e8527950198242c93c02201a9",
    "ai_summary": "Kitty岛小乔：女仆装服务，颜值身材中上，尺度到位但态度较冷淡，综合体验中等。",
    "text_preview": "#牌局复盘\n\n【麻友】：听泉子\n【棋牌室】：#Kitty岛\n【麻将搭子】：#小乔\n【搭子链接】：https://t.me/hello_kittynvpuguan/33628\n【台费】：工兵价\n【胡牌牌型】：#大班\n【牌局特点】：#女仆装 #细枝硕果\n【各项得分】：（0-10，6 为及格，对应大班）\n  环境：8\n  人照：7\n  身材：8\n  皮肤：8\n  态度：6\n  敏感度：6\n  抽烟：无\n  纹身：无\n  各种钉：无\n【综合得分】：7\n【牌局体验】：\n\n人照7，ot视频开了美颜瘦脸，被动配合型，合理的要求基本上都能满足，亲胸无反馈，自述性冷淡。尺度其实给到位了但是态度一般，服务意识待加"
  },
  {
    "source": "npmjzjfp",
    "source_title": "麻将战绩",
    "msg_id": 2298,
    "shop": "Kitty岛",
    "girl": "小乔",
    "girl_link": "https://t.me/hello_kittynvpuguan/33628",
    "review_link": "https://t.me/npmjzjfp/2298",
    "shop_tg": "https://t.me/hello_kittynvpuguan",
    "time": "08:45",
    "fp": "a01419e909b1792eab2cb41e59eebb93",
    "ai_summary": "杭州Kitty岛女仆馆小乔，着女仆装服务，态度亲切、尺度适中，综合体验良好。",
    "text_preview": "#牌局复盘\n\n【麻友】：Padishah Shahanshah\n【棋牌室】：#Kitty岛\n【麻将搭子】：#小乔\n【搭子链接】：https://t.me/hello_kittynvpuguan/33628\n【台费】：450/h\n【胡牌牌型】：#大班\n【牌局特点】：#女仆装\n【各项得分】：（0-10，6 为及格，对应大班）\n  环境：8\n  人照：7\n  身材：7\n  皮肤：8\n  态度：8\n  敏感度：8\n  抽烟：无\n  纹身：无\n  各种钉：无\n【综合得分】：8\n【牌局体验】：见到小乔真人，她和最好看的那张OOTD还是有点差距的。真人的脸属于偏大偏圆的类型，高于路人水准。这天她还穿了女仆装"
  },
  {
    "source": "whointheworldami",
    "source_title": "西湖歌舞几时休",
    "msg_id": 5446,
    "shop": "甜屿",
    "girl": "夏迷",
    "girl_link": "",
    "review_link": "https://t.me/whointheworldami/5446",
    "shop_tg": "https://t.me/mengyouxianjing1",
    "time": "10:04",
    "fp": "001032d6784698c2cce2f47ef821a769",
    "ai_summary": "甜屿女仆夏迷，素人甜妹微BBW身材、皮肤白滑，服务主动配合、氛围温馨，整体清纯自然体验佳。",
    "text_preview": "#No1584\n店铺：#甜屿\n女仆：#夏迷\n店铺链接:   t.me/mengyouxianjing1\n店铺资料： t.me/standingmanhz/1045\n类型：#素人  #甜妹  #微bbw\n价格：工兵450\n出击人：#小灰灰\n出击时间：2026.07\n环境： B，经典loft\n人照相似度：人照8.5\n罩杯：胸B\n身材：微bbw\n身高：164\n体重：107\n皮肤：白度 很白，弹性 很弹，平滑度 很滑。\n态度：A\n聊天交流：乖乖甜妹  偏内向\n敏感处: 奈头\n抽烟：无\n纹身：无\n唇钉舌钉：无\n吻技：小蟒蛇\n\n**🌱初见**\n    昨天闲逛，刷到甜屿的新人模卡，一眼就知道是好妹妹，一问"
  },
  {
    "source": "whointheworldami",
    "source_title": "西湖歌舞几时休",
    "msg_id": 5444,
    "shop": "甜屿",
    "girl": "夏弥",
    "girl_link": "",
    "review_link": "https://t.me/whointheworldami/5444",
    "shop_tg": "https://t.me/mengyouxianjing1",
    "time": "09:48",
    "fp": "92614a5b42e319461481c018b0d1f36e",
    "ai_summary": "甜屿女仆夏弥，甜美清纯颜值高，素人但互动积极，服务自然亲切，综合体验推荐。",
    "text_preview": "#No1583\n店铺：#甜屿\n女仆：#夏弥\n店铺链接:   t.me/mengyouxianjing1\n店铺资料： t.me/standingmanhz/1045\n类型：#邻家妹妹 #bbw \n价格：工兵450\n出击人：四个2带两个王\n出击时间：2026.7.14\n首次服役时间：2026.7.14\n环境： A\n人照相似度：人照 8\n罩杯：胸C，大熊\n身材：BBW身材\n身高：164\n体重：107\n皮肤：白度（很白）     弹性（很弹）    平滑度（很滑）\n敏感处: 私处\n抽烟：无\n纹身：无\n唇钉舌钉：无\n吻技：正常\n\n**🌱初见**\n    被摘照片吸引了，青春甜美的样子，那没办法了，很喜欢"
  },
  {
    "source": "whointheworldami",
    "source_title": "西湖歌舞几时休",
    "msg_id": 5442,
    "shop": "甜屿",
    "girl": "夏弥",
    "girl_link": "",
    "review_link": "https://t.me/whointheworldami/5442",
    "shop_tg": "https://t.me/mengyouxianjing1",
    "time": "09:34",
    "fp": "14a157aae6145010eebfc0663eb96415",
    "ai_summary": "",
    "text_preview": "#No1582\n店铺：#甜屿\n女仆：#夏弥\n店铺链接:   t.me/mengyouxianjing1\n店铺资料： t.me/standingmanhz/1045\n类型：#清纯可爱 #纯欲甜妹 #小M\n价格：600/h\n出击人：#cdd\n出击时间：2026.07.13\n首次服役时间：2026.07\n环境： A\n人照相似度：人照8\n罩杯：胸b+，柔软丰满\n身材：微胖丰满，臀部大，曲线优美\n身高：164\n体重：107\n皮肤：白嫩紧致，光滑\n敏感处: 耳朵，乳头\n抽烟：无\n纹身：无\n唇钉舌钉：无\n吻技：中蟒蛇\n\n**🌱初见**\n    刷tg偶然刷到甜屿家的妹妹，夏迷的摩卡第一眼就吸引到了我，看起来"
  },
  {
    "source": "whointheworldami",
    "source_title": "西湖歌舞几时休",
    "msg_id": 5440,
    "shop": "靡音",
    "girl": "饱饱",
    "girl_link": "",
    "review_link": "https://t.me/whointheworldami/5440",
    "shop_tg": "https://t.me/miyinpb",
    "time": "09:06",
    "fp": "9ae6f01b1e646e3305749a4a85d08cd7",
    "ai_summary": "靡音馆饱饱：高挑瘦削、耳胸敏感，御姐外形配温柔青涩气质，聊天自然热情，服务配合度高，整体体验优质。",
    "text_preview": "#No1581\n店铺：#靡音\n女仆：#饱饱\n店铺链接:   t.me/miyinjl\n店铺资料： t.me/standingmanhz/1308\n类型：#甜御\n价格：600/h\n出击人：#kewu\n出击时间：2026.7\n环境： s，公寓\n人照相似度：人照9\n罩杯：胸a\n身材：高瘦，腰细，腿长\n身高：168\n体重：88\n皮肤：正常\n态度：S\n聊天交流：聊的不错\n敏感处: 耳朵胸敏感\n抽烟：有\n纹身：无\n唇钉舌钉：有\n吻技：无🐍\n\n**🌱初见**\n    饱饱堵车晚了几分钟，一进门红色艳裙搭配黑丝红手套非常抢眼。刚开始聊天妹妹性格跟御姐外形挺反差，说话很温柔，也很可爱有点羞涩，刚做不久，青涩感十"
  },
  {
    "source": "whointheworldami",
    "source_title": "西湖歌舞几时休",
    "msg_id": 5438,
    "shop": "夜无眠",
    "girl": "娜娜",
    "girl_link": "",
    "review_link": "https://t.me/whointheworldami/5438",
    "shop_tg": "https://t.me/Sleeplessnight_youyou",
    "time": "08:51",
    "fp": "9d1233cdd6801107cdec9f1f316b2ece",
    "ai_summary": "夜无眠娜娜：素人嫩妹，皮肤超滑白嫩、C罩杯触感佳，性格乖巧羞涩，整体体验自然真实。",
    "text_preview": "#No1580\n店铺：#夜无眠\n女仆：#娜娜\n店铺链接:   t.me/Sleeplessnight_youyou\n店铺资料： t.me/standingmanhz/1048\n类型：#嫩妹 #素人 #皮肤巨滑\n价格：工兵450\n出击人：#小灰灰\n出击时间：2026.07\n环境： B，经典loft\n人照相似度：人照8.5\n罩杯：胸C\n身材：蜂腰大臀\n身高：165\n体重：110\n皮肤：白度 很白，弹性 Q弹，平滑度 超滑。\n态度：A\n聊天交流：乖乖妹  手游宅女  恋爱经验少\n敏感处: 奈头 大腿根部 \n抽烟：无\n纹身：无\n唇钉舌钉：无\n吻技：小蟒蛇\n\n**🌱初见**\n    这次早来了半小时，和"
  },
  {
    "source": "whointheworldami",
    "source_title": "西湖歌舞几时休",
    "msg_id": 5436,
    "shop": "星茶荟",
    "girl": "伊伊",
    "girl_link": "",
    "review_link": "https://t.me/whointheworldami/5436",
    "shop_tg": "https://t.me/xingchahui888",
    "time": "08:39",
    "fp": "75da72732fd643325459994273152200",
    "ai_summary": "星茶荟伊伊服务热情、配合度高，皮肤细腻敏感度佳，整体体验优质。",
    "text_preview": "#No1579\n店铺：#星茶荟\n女仆：#伊伊\n店铺链接:   t.me/xingchahui888\n店铺资料： t.me/standingmanhz/1098\n类型：#bbw\n价格：工兵450/h\n出击人：#1\n出击时间：2025.06\n环境： S，小区房\n人照相似度：人照8\n罩杯：B\n身材：#bbw\n身高：167\n体重：116\n皮肤：较白，弹性（正常），平滑度（较滑）。\n态度：A，配合度高\n聊天交流：挺会聊的\n敏感处: 胸敏感\n抽烟：有，未闻到烟味\n纹身：没看见\n唇钉舌钉：无\n吻技：吻技一般水平\n\n**🌱初见**\n    看到伊伊的时候看她的长相个打扮是个御姐，不过声音很柔很好听。先简单熟悉"
  },
  {
    "source": "nvpu_seek",
    "source_title": "女仆探索",
    "msg_id": 482,
    "shop": "寿司",
    "girl": "诺诺岛",
    "girl_link": "",
    "review_link": "https://t.me/nvpu_seek/482",
    "shop_tg": "https://t.me/nvpu_seek",
    "time": "01:46",
    "fp": "4c6dff7d2810a3bb07189b8938d90cb4",
    "ai_summary": "诺诺岛女仆馆妹妹诺诺，颜值身材俱佳、情绪价值高、服务配合度好，综合体验优秀。",
    "text_preview": "[#寿司#诺诺岛#西湖#1H](https://t.me/nuoyannvpu)\n\n颜值：8.5分（班花，T2上）\n身材：9分（胸b粉嫩苗条）\n吻技：9分（大蟒蛇一直亲）\n情绪：10分（爱笑好相处）\n敏感度：9分（敏感反馈足）\n配合度：9分（非常配合）\n\n测评拖了几天没发，本想藏菜复刷后再发，结果过了一阵子竟然直接退役了，了解了一下说是房租费挣够了，好吧，作为备忘还是发一下吧，希望有缘还能再见。上钟体验就不说了，情绪价值溢出，尺度也够用。**颜值身材T2上，标大拉满的好妹妹。\n**\n**推荐指数：四星，非常推荐**"
  },
  {
    "source": "nvpu_seek",
    "source_title": "女仆探索",
    "msg_id": 481,
    "shop": "小乔",
    "girl": "kitty岛",
    "girl_link": "",
    "review_link": "https://t.me/nvpu_seek/481",
    "shop_tg": "https://t.me/nvpu_seek",
    "time": "01:21",
    "fp": "ff515afc8028edf58e442a94878dbb9a",
    "ai_summary": "小乔（kitty岛）：颜值身材俱佳、配合度高，但服务意识较弱、情绪欠佳，整体中规中矩。",
    "text_preview": "[#小乔#kitty岛#拱墅#1H](https://t.me/hello_kittynvpuguan)\n\n颜值：8.2分（班花，T2中）\n身材：9分（细枝硕果）\n吻技：8分（被动配合）\n情绪：5分（被迫营业既视感）\n敏感度：6分（反馈较少）\n配合度：8.5分（非常配合）\n\n人照8，被动配合型，合理的要求基本上都能满足，亲胸无反馈，自述性冷淡。尺度其实给到位了但是态度一般，服务意识待加强，被迫营业既视感，不怎么爱笑，不知道是心情不好还是被卡了，感觉是一个很有自己个性的女孩子。值得注意⚠️的是妹妹比较讨厌烟味，可能是命中了她的雷区吧。**颜值身材T2中，尺度标大+。**\n\n**推荐指数：三星，中"
  },
  {
    "source": "nvpu_seek",
    "source_title": "女仆探索",
    "msg_id": 480,
    "shop": "七七",
    "girl": "kitty岛",
    "girl_link": "",
    "review_link": "https://t.me/nvpu_seek/480",
    "shop_tg": "https://t.me/nvpu_seek",
    "time": "00:43",
    "fp": "a4e86fb39712fc96b0f1bc127fd8c5ef",
    "ai_summary": "七七（Kitty岛）：颜值身材T2上，服务热情配合度高，整体体验优秀，强烈推荐。",
    "text_preview": "[#七七#kitty岛#拱墅#1H](https://t.me/hello_kittynvpuguan)\n\n颜值：8.8分（班花，T2上）\n身材：9分（胸c粉嫩）\n吻技：9（中蟒蛇一直亲）\n爱好：9（无烟味无纹身无钉）\n情绪：9分（爱笑好相处）\n敏感度：9（敏感水润）\n配合度：9分（非常配合）\n\n素人，卸甲顺畅，滔滔不绝，潜力满姐，会复刷。**颜值身材T2上，标大隔裤拉满的好妹妹！**\n\n**推荐指数：五星，强烈推荐**"
  }
]