[
  {
    "source": "npmjzjfp",
    "source_title": "麻将战绩",
    "msg_id": 1016,
    "shop": "YOYO",
    "girl": "雯雯",
    "girl_link": "https://t.me/hznplaq/10460",
    "review_link": "https://t.me/npmjzjfp/1016",
    "shop_tg": "https://t.me/hznplaq",
    "time": "23:29",
    "fp": "c83241018f29090761ec0b113fe60375",
    "ai_summary": "YOYO女仆馆雯雯妹妹服务热情主动，胸下敏感、娇羞可爱，环境整洁、态度佳，综合体验良好。",
    "text_preview": "#牌局复盘\n\n【麻友】：战斗暴龙兽\n【棋牌室】：#YOYO\n【麻将搭子】：#雯雯\n【搭子链接】：https://t.me/hznplaq/10460\n【台费】：600\n【胡牌牌型】： #大班\n【牌局特点】：#胸下敏感 #小害羞\n【各项得分】：（0-10，6 为及格）\n  环境：7.5\n  人照：7.5\n  身材：7\n  皮肤：7\n  态度：8.5\n  敏感度：8\n  抽烟：无\n  纹身：无\n  各种钉：无\n【综合得分】：7.5\n【牌局体验】：\n想吃嘴子了，看到YOYO上新，果断约之。妹妹当天的穿搭不错，可爱小裙子，妆化的刚好，主动拆漱口水然后附上纸巾一起给我。闲聊1分钟之后直接吻了上去，从衣服"
  },
  {
    "source": "npmjzjfp",
    "source_title": "麻将战绩",
    "msg_id": 1015,
    "shop": "吉野岛",
    "girl": "萌面高手",
    "girl_link": "https://t.me/jiyedao258/183663",
    "review_link": "https://t.me/npmjzjfp/1015",
    "shop_tg": "https://t.me/jiyedao258",
    "time": "22:54",
    "fp": "faef751f286afbf11d9687802ecbba39",
    "ai_summary": "萌面高手服务热情细致，OOTD精致、互动有趣，综合体验佳，环境与态度均获好评。",
    "text_preview": "#牌局复盘\n\n【麻友】：Padishah Shahanshah\n【棋牌室】：#吉野岛\n【麻将搭子】：#萌面高手\n【搭子链接】：https://t.me/jiyedao258/183663\n【台费】：700/2h\n【胡牌牌型】： #大班 \n【牌局特点】：#女大学生\n【各项得分】：（0-10，6 为及格，对应大班）\n  环境：8\n  人照：7\n  身材：8\n  皮肤：8\n  态度：8\n  敏感度：8\n  抽烟：无\n  纹身：无\n  各种钉：无\n【综合得分】：8\n【牌局体验】：\n萌面高手的OOTD历来都惊为天人。我本来想指定那套海军服的，结果客服说她衣服都是穿一天就扔了。等到萌面高手一边做着奇怪的动"
  },
  {
    "source": "npmjzjfp",
    "source_title": "麻将战绩",
    "msg_id": 1014,
    "shop": "悠觅",
    "girl": "小水",
    "girl_link": "https://t.me/Youmeenp002/33435",
    "review_link": "https://t.me/npmjzjfp/1014",
    "shop_tg": "https://t.me/Youmeenp002",
    "time": "22:50",
    "fp": "260fa4acc3c5ed38eb8e8ca50de85ea3",
    "ai_summary": "悠觅女仆馆小水：御姐气质、配合度高、服务细致，环境与态度获好评，综合体验优秀。",
    "text_preview": "#牌局复盘\n\n【麻友】：风云\n【棋牌室】：#悠觅\n【麻将搭子】：#小水\n【搭子链接】：https://t.me/Youmeenp002/33435\n【台费】：10+550\n【胡牌牌型】：#大班\n【牌局特点】：#大蟒蛇 #配合 #御姐\n【各项得分】：\n  环境：8\n  人照：8.5\n  身材：7\n  皮肤：7\n  态度：8\n  敏感度：8\n  抽烟：有\n  纹身：有\n  各种钉：无\n【综合得分】：8.8\n【牌局体验】：\n看了模卡一直想点下小水，这次特地抽空来点一下。小水本人是一个大长腿御姐，但经过聊天后发现其实也是挺可爱的女孩子。钟上简单破冰后开始亲，瞬间感觉不对了，舌头很软且超级灵活，也是一个"
  },
  {
    "source": "npmjzjfp",
    "source_title": "麻将战绩",
    "msg_id": 1013,
    "shop": "库洛",
    "girl": "小黄",
    "girl_link": "https://t.me/kuluokeke/206190",
    "review_link": "https://t.me/npmjzjfp/1013",
    "shop_tg": "https://t.me/kulook_chance",
    "time": "22:50",
    "fp": "165713ff3f052ebf6dfc2534958e5698",
    "ai_summary": "库洛小黄：黑丝高跟、颜值高、笑点低且敏感，服务自然单纯，综合体验8.7分。",
    "text_preview": "#牌局复盘\n\n【麻友】：风云\n【棋牌室】：#库洛\n【麻将搭子】：#小黄\n【搭子链接】：https://t.me/kuluokeke/206190\n【台费】：600\n【胡牌牌型】：#大班\n【牌局特点】：#御姐脸 #甜妹 #可爱\n【各项得分】：\n  环境：8\n  人照：8\n  身材：7\n  皮肤：7.5\n  态度：7.5\n  敏感度：8.5\n  抽烟：无\n  纹身：无\n  各种钉：无\n【综合得分】：8.7\n【牌局体验】：\n因为下雨堵车严重导致我迟到了很久，就只能补位最后一个尾钟。等了许久后见到了小黄，穿着黑丝小高跟，人都快有1.78m了，虽然妆有点花了，但还是能看出来小黄的漂亮，颜值确实很不错，不"
  },
  {
    "source": "npmjzjfp",
    "source_title": "麻将战绩",
    "msg_id": 1012,
    "shop": "YOYO",
    "girl": "橘子",
    "girl_link": "https://t.me/hznplaq/10492",
    "review_link": "https://t.me/npmjzjfp/1012",
    "shop_tg": "https://t.me/hznplaq",
    "time": "22:40",
    "fp": "6df3d6ac78e844f46ca2b30f34440704",
    "ai_summary": "YOYO女仆馆橘子妹妹，皮肤白滑、身材匀称，服务配合度尚可但主动性不足，整体印象中上。",
    "text_preview": "#牌局复盘\n\n【麻友】：胖虎\n【棋牌室】：#YOYO\n【麻将搭子】：#橘子\n【搭子链接】：https://t.me/hznplaq/10492\n【台费】：1000\n【胡牌牌型】：#大班\n【牌局特点】：#素人感\n【各项得分】：（0-10，6 为及格）\n  环境：8（公寓大床）\n  人照：7，模卡高P，真人黄毛短发浓妆有点显老\n  身材：8，163/90/B，身材匀称有曲线\n  皮肤：8，白度一般，平滑度高\n  态度：7，尺度内配合\n  敏感度：7，一般\n  抽烟：无\n  纹身：无\n  各种钉：无\n【综合得分】：7\n【牌局体验】：\n提前约好的妹妹鸽了，看到YOYO新人橘子的模卡还不错，且客服回复速"
  },
  {
    "source": "npmjzjfp",
    "source_title": "麻将战绩",
    "msg_id": 1011,
    "shop": "库洛",
    "girl": "小黄",
    "girl_link": "https://t.me/kuluokeke/203904?single",
    "review_link": "https://t.me/npmjzjfp/1011",
    "shop_tg": "https://t.me/kulook_chance",
    "time": "21:57",
    "fp": "26d9f2d13fe81315ae8ff46234b8cae6",
    "ai_summary": "库洛小黄：JK装黑丝、青春活力、敏感度高，颜值情绪俱佳，综合评分8.698。",
    "text_preview": "#牌局复盘\n\n【麻友】：#爱椰\n【棋牌室】：#库洛\n【麻将搭子】：#小黄\n【搭子链接】：https://t.me/kuluokeke/203904?single\n【台费】：大班\n【胡牌牌型】：#大班\n【牌局特点】：#素人女大\n【各项得分】：（0-10，6 为及格，对应大班）\n  环境：7.9\n  人照：8.0\n  身材：7.9\n  皮肤：8.0\n  态度：8.0\n  敏感度：8.2\n  抽烟：无\n  纹身：无\n  各种钉：无\n【综合得分】：8.698\n【牌局体验】：应该算是库洛目前版本中最好看的女孩子，女大，无纹身不抽烟不精神。由于每晚都需要回学校，所以导致下班较早，来了好多天一直约不上时间。"
  },
  {
    "source": "npmjzjfp",
    "source_title": "麻将战绩",
    "msg_id": 1010,
    "shop": "月亮",
    "girl": "莎莎",
    "girl_link": "https://t.me/Changejieyouchat/643972",
    "review_link": "https://t.me/npmjzjfp/1010",
    "shop_tg": "https://t.me/Changejieyouchat",
    "time": "21:39",
    "fp": "574eca4915a5f8ec5db1b58ff6abc8f6",
    "ai_summary": "莎莎妹妹服务自然亲切，环境满分、态度佳，综合体验8.5分，属熟人复刷型纯爱局。",
    "text_preview": "#牌局复盘\n\n【麻友】：Ban\n【棋牌室】：#月亮\n【麻将搭子】：#莎莎\n【搭子链接】：https://t.me/Changejieyouchat/643972\n【台费】：1200\n【胡牌牌型】：#大班\n【牌局特点】：#大蟒蛇\n【各项得分】：（0-10，6 为及格）\n  环境：10\n  人照：9\n  身材：8\n  皮肤：8\n  态度：8\n  敏感度：7\n  抽烟：无\n  纹身：无\n  各种钉：无\n【综合得分】：8.5\n【牌局体验】：莎莎属于约了好多次了，我冲着身高去的，这次今年来了第三次复刷，主要本人要加班，临时定了民宿外派，见面不说啥了，直接进入正题，慢慢的脱了连衣裙，卸甲顺利，摸了摸下面没"
  },
  {
    "source": "npmjzjfp",
    "source_title": "麻将战绩",
    "msg_id": 1009,
    "shop": "月亮",
    "girl": "UU",
    "girl_link": "https://t.me/Changejieyouchat/643974",
    "review_link": "https://t.me/npmjzjfp/1009",
    "shop_tg": "https://t.me/Changejieyouchat",
    "time": "21:36",
    "fp": "aa8ff0aa43783d736d36ca3e1d7aee48",
    "ai_summary": "月亮女仆馆UU妹妹，环境佳、互动自然有亲和力，综合体验优秀。",
    "text_preview": "#牌局复盘\n\n【麻友】：Ban\n【棋牌室】：#月亮\n【麻将搭子】：#UU\n【搭子链接】： https://t.me/Changejieyouchat/643974\n【台费】：600\n【胡牌牌型】：#大班\n【牌局特点】：#大蟒蛇\n【各项得分】：（0-10，6 为及格）\n  环境：10\n  人照：8.5\n  身材：8\n  皮肤：7\n  态度：8\n  敏感度：8\n  抽烟：有\n  纹身：无\n  各种钉：无\n【综合得分】：8.5\n【牌局体验】：属实UU御姐身材，该有的地方都有，去头无敌，月亮唯一缺点就是房间太矮，不管楼上楼下碰头，但是环境无敌，UU见面不冷场，会骑乘式抱抱，亲吻的时候拉丝了都，然后搂着"
  },
  {
    "source": "npmjzjfp",
    "source_title": "麻将战绩",
    "msg_id": 1008,
    "shop": "妹调日记",
    "girl": "图图",
    "girl_link": "https://t.me/galgamemeitiaoriji/7130?single",
    "review_link": "https://t.me/npmjzjfp/1008",
    "shop_tg": "https://t.me/meitiaoriji",
    "time": "21:05",
    "fp": "92c55e214a19f2d4f500bd70b640388d",
    "ai_summary": "",
    "text_preview": "#牌局复盘\n\n【麻友】：圭0\n【棋牌室】：#妹调日记\n【麻将搭子】：#图图\n【搭子链接】：https://t.me/galgamemeitiaoriji/7130?single\n【台费】：500\n【胡牌牌型】：#大班\n【牌局特点】：#敏感\n【各项得分】：（0-10，6 为及格）\n  环境：8.5\n  人照：7.5\n  身材：7.8\n  皮肤：7.5\n  态度：8\n  敏感度：8.5\n  抽烟：有\n  纹身：无\n  各种钉：有\n【综合得分】：8\n【牌局体验】：前两天刷妹调日记看到图图刚上线，照片里那张呆萌脸配160/80/B的数字，一眼就是那种清纯小新人，我本来还犹豫，结果看到发出来的测评，果断"
  },
  {
    "source": "npmjzjfp",
    "source_title": "麻将战绩",
    "msg_id": 1007,
    "shop": "千寻",
    "girl": "小喵",
    "girl_link": "https://t.me/hangz4325/4531?single",
    "review_link": "https://t.me/npmjzjfp/1007",
    "shop_tg": "https://t.me/hangz4325",
    "time": "20:45",
    "fp": "69d23c94aa0abfab6fb5774efb63e088",
    "ai_summary": "千寻馆小喵妹妹，白丝裙装+唇钉反差萌，态度亲和、服务主动，环境与体验俱佳。",
    "text_preview": "#牌局复盘\n【麻友】：水（必须实名）\n【棋牌室】：#千寻\n【麻将搭子】：#小喵\n【搭子链接】：https://t.me/hangz4325/4531?single\n【台费】：200筹码+900\n【胡牌牌型】：#大班\n【牌局特点】：#小蟒蛇 #素人感\n【各项得分】：（0-10，6 为及格）\n  环境：9\n  人照：8\n  身材：7\n  皮肤：7\n  态度：9\n  敏感度：8\n  抽烟：有\n  纹身：无\n  各种钉：有唇钉\n【综合得分】：8（0-10，6 为及格）\n【牌局体验】：\n小楼一夜听春雨，深巷明朝卖杏花，杭州的天气总是让人捉摸不透，上午阳光正好，约了个钟，中午便开始下雨了，不过还好，就在地"
  },
  {
    "source": "npmjzjfp",
    "source_title": "麻将战绩",
    "msg_id": 1006,
    "shop": "诺诺岛",
    "girl": "芊芊",
    "girl_link": "https://t.me/nuoyannvpu/27978",
    "review_link": "https://t.me/npmjzjfp/1006",
    "shop_tg": "https://t.me/nuoyannvpu",
    "time": "20:39",
    "fp": "7d6a354213ec48ef7fa4245a1d9c1d55",
    "ai_summary": "杭州诺诺岛芊芊：白幼瘦外形出众，情绪价值高、性格乖巧，服务细腻贴心，综合体验优质。",
    "text_preview": "#牌局复盘\n\n【麻友】：圭0\n【棋牌室】：#诺诺岛\n【麻将搭子】：#芊芊\n【搭子链接】：https://t.me/nuoyannvpu/27978\n【台费】：优惠券800\n【胡牌牌型】：#大班\n【牌局特点】：#配合 #尺度 #白幼瘦\n【各项得分】：\n  环境：7\n  人照：8\n  身材：7.5\n  皮肤：8\n  态度：8\n  敏感度：8\n  抽烟：无\n  纹身：无\n  各种钉：无\n【综合得分】：8\n【牌局体验】：\n【评测】：前两天在诺诺岛刷到芊芊的cos照就直接心动了，那张白幼瘦的脸配165/78的数字，直接就心动了，刚好看到有空位就果断约了。到店后芊芊带我上楼，真人比照片还幼，皮肤白得发光，"
  },
  {
    "source": "hznp_college",
    "source_title": "杭州女仆学院",
    "msg_id": 1814,
    "shop": "文文",
    "girl": "塔菲喵",
    "girl_link": "",
    "review_link": "https://t.me/hznp_college/1814",
    "shop_tg": "https://t.me/hznp_college",
    "time": "21:41",
    "fp": "334b66187f12ad5305509904ed191179",
    "ai_summary": "塔菲喵文文妹妹：颜值高、情绪价值足、萝莉素人风格，聊天自然有女友感，环境与服务俱佳。",
    "text_preview": "【2026年女仆大学招生考试】\n———————————————\n考生姓名：#文文\n考试日期：2026.4\n考试地点：#塔菲喵\nt.me/ouruola123\n考试区域：#拱墅\n监考老师：#幸福\n是否推荐：#推荐\n总得分：51.5+35.5+15\n———————————————\n第一题：标大篇（60分）\n颜值：8.5（人照基本一致）\n身材：8.5（皮肤好，a+，萝莉）\n爱好：9（没烟味，未见纹身）\n吻技：8（还算配合，不是很主动）\n敏感度：8.5（比较敏感）\n情绪价值：9（素人妹妹，挺会聊天的，情绪价值拉满）\n———————————————\n第二题：服务篇（40分）\n店内环境：9（还可以）\n客服"
  }
]