[
  {
    "source": "npmjzjfp",
    "source_title": "麻将战绩",
    "msg_id": 1983,
    "shop": "星茶荟",
    "girl": "火柴",
    "girl_link": "https://t.me/xingchahui888/54695",
    "review_link": "https://t.me/npmjzjfp/1983",
    "shop_tg": "https://t.me/xingchahui888",
    "time": "08:43",
    "fp": "9e2a0144b1916e95452f8d2b0a73ae0c",
    "ai_summary": "星茶荟火柴妹妹服务细致、舌钉特色鲜明，清纯治愈系风格突出，综合体验良好。",
    "text_preview": "#牌局复盘\n\n【麻友】：Stephen Howard\n【棋牌室】：#星茶荟\n【麻将搭子】：#火柴\n【搭子链接】：https://t.me/xingchahui888/54695\n【台费】：500新人测评价\n【胡牌牌型】：#大班\n【牌局特点】：#清纯 #体贴 #治愈系\n【各项得分】：\n  环境：8\n  人照：8\n  身材：8.5\n  皮肤：8\n  态度：8.5\n  敏感度：8\n  抽烟：无\n  纹身：无\n  各种钉：有，舌钉，唇钉\n【综合得分】：8 （治愈系美少女）\n【牌局体验】：虽然这周已经冲了倩倩，奈何今天又躁动不安，客服说店里来了新人要不要体验下，这还说啥，果断冲了。妹妹和倩倩一样也是穿着"
  },
  {
    "source": "npmjzjfp",
    "source_title": "麻将战绩",
    "msg_id": 1982,
    "shop": "Kitty岛",
    "girl": "CC",
    "girl_link": "https://t.me/hello_kittynvpuguan/27201",
    "review_link": "https://t.me/npmjzjfp/1982",
    "shop_tg": "https://t.me/hello_kittynvpuguan",
    "time": "06:39",
    "fp": "c3817ad4a4cfeb7964d6d935b5e1a4b6",
    "ai_summary": "Kitty岛CC妹妹服务热情主动，高挑白瘦、皮肤细腻，舌钉增添个性，整体体验女友感强，综合评分8.4分。",
    "text_preview": "#牌局复盘\n\n【麻友】：Finn\n【棋牌室】：#Kitty岛\n【麻将搭子】：#CC\n【搭子链接】：https://t.me/hello_kittynvpuguan/27201\n【台费】：500新人价\n【胡牌牌型】：#大班\n【牌局特点】：#白瘦 #女友感\n【各项得分】：（0-10，6 为及格，对应大班）\n  环境：7.3\n  人照： 8.5\n  身材：8.5\n  皮肤：8.5\n  态度：8.3\n  敏感度：8.5\n  抽烟：有\n  纹身：有\n  各种钉：有\n【综合得分】：8.4（0-10，6 为及格）\n【牌局体验】：\n颜值：颜值T2中，算是小甜妹，妆容有提升空间，一侧有小虎牙\n舌吻：主动热情，舌"
  },
  {
    "source": "npmjzjfp",
    "source_title": "麻将战绩",
    "msg_id": 1981,
    "shop": "库洛",
    "girl": "章章",
    "girl_link": "https://t.me/kuluokeke/228190",
    "review_link": "https://t.me/npmjzjfp/1981",
    "shop_tg": "https://t.me/kulook_chance",
    "time": "00:47",
    "fp": "141c5fcf2652b92961b54ab088f2256a",
    "ai_summary": "",
    "text_preview": "#牌局复盘\n\n【麻友】：战斗暴龙兽\n【棋牌室】：#库洛\n【麻将搭子】：#章章\n【搭子链接】：https://t.me/kuluokeke/228190\n【台费】：700，竞拍2免1\n【胡牌牌型】：#大班\n【牌局特点】：#情绪价值 #皮肤滑\n【各项得分】：（0-10，6 为及格，对应大班）\n  环境：7.5\n  人照：8\n  身材：8\n  皮肤：9\n  态度：8.5\n  敏感度：7\n  抽烟：无\n  纹身：无\n  各种钉：无\n【综合得分】：8\n【牌局体验】：\n端午节陪完家人，那肯定要陪一下妹妹，最近需要心灵净化，果断选择章章。轻车熟路到店，因为之前点过，妹妹说哇你怎么来啦，辣条音很对味，我没说话"
  },
  {
    "source": "npmjzjfp",
    "source_title": "麻将战绩",
    "msg_id": 1980,
    "shop": "软糖熊",
    "girl": "kitty",
    "girl_link": "https://t.me/ruantangxiong888/96687",
    "review_link": "https://t.me/npmjzjfp/1980",
    "shop_tg": "https://t.me/ruantangxiong888",
    "time": "00:30",
    "fp": "ab8deb3eff920e8637f8712b9eaa7b9a",
    "ai_summary": "软糖熊馆Kitty妹妹，眼镜黑丝造型亮眼，舌吻技术娴熟、情绪饱满，综合体验9.5分。",
    "text_preview": "#牌局复盘\n\n【麻友】：Andy(岸)\n【棋牌室】：#软糖熊\n【麻将搭子】：#kitty\n【搭子链接】：https://t.me/ruantangxiong888/96687\n【台费】：600\n【胡牌牌型】：#大班\n【牌局特点】：#大蟒蛇\n【各项得分】：（0-10，6 为及格）\n  环境：8\n  人照：9\n  身材：9\n  皮肤：10\n  态度：10\n  敏感度：9\n  抽烟：无\n  纹身：无\n  各种钉：无\n【综合得分】：9.5\n【牌局体验】：\n本来今天下午约没约上，晚上约了，结果前面客人又晚到，多等快半个小时，但见到妹妹体验下来，证明等待没白费。\nKitty妹妹团播出身，颜值身材气质在女仆"
  }
]